{
    "swagger": "2.0",
    "info": {
        "description": "REST API untuk CRUD produk menggunakan net/http dan ServeMux",
        "title": "Product API",
        "contact": {},
        "version": "1.0"
    },
    "host": "localhost:8081",
    "basePath": "/",
    "paths": {
        "/products": {
            "get": {
                "description": "Menampilkan semua produk yang ada",
                "produces": [
                    "application/json"
                ],
                "tags": [
                    "products"
                ],
                "summary": "Ambil daftar produk",
                "responses": {
                    "200": {
                        "description": "OK",
                        "schema": {
                            "type": "array",
                            "items": {
                                "$ref": "#/definitions/model.Product"
                            }
                        }
                    }
                }
            },
            "post": {
                "description": "Menambahkan produk baru ke sistem",
                "consumes": [
                    "application/json"
                ],
                "produces": [
                    "application/json"
                ],
                "tags": [
                    "products"
                ],
                "summary": "Buat produk baru",
                "parameters": [
                    {
                        "description": "Data produk",
                        "name": "product",
                        "in": "body",
                        "required": true,
                        "schema": {
                            "$ref": "#/definitions/model.ProductCreateRequest"
                        }
                    }
                ],
                "responses": {
                    "201": {
                        "description": "Created",
                        "schema": {
                            "$ref": "#/definitions/model.Product"
                        }
                    },
                    "400": {
                        "description": "Bad Request",
                        "schema": {
                            "type": "object",
                            "additionalProperties": {
                                "type": "string"
                            }
                        }
                    }
                }
            }
        },
        "/products/{id}": {
            "get": {
                "description": "Menampilkan detail produk berdasarkan ID",
                "produces": [
                    "application/json"
                ],
                "tags": [
                    "products"
                ],
                "summary": "Ambil detail produk",
                "parameters": [
                    {
                        "type": "integer",
                        "description": "Product ID",
                        "name": "id",
                        "in": "path",
                        "required": true
                    }
                ],
                "responses": {
                    "200": {
                        "description": "OK",
                        "schema": {
                            "$ref": "#/definitions/model.Product"
                        }
                    },
                    "404": {
                        "description": "Not Found",
                        "schema": {
                            "type": "object",
                            "additionalProperties": {
                                "type": "string"
                            }
                        }
                    }
                }
            },
            "put": {
                "description": "Mengubah data produk berdasarkan ID",
                "consumes": [
                    "application/json"
                ],
                "produces": [
                    "application/json"
                ],
                "tags": [
                    "products"
                ],
                "summary": "Update produk",
                "parameters": [
                    {
                        "type": "integer",
                        "description": "Product ID",
                        "name": "id",
                        "in": "path",
                        "required": true
                    },
                    {
                        "description": "Data produk baru",
                        "name": "product",
                        "in": "body",
                        "required": true,
                        "schema": {
                            "$ref": "#/definitions/model.ProductUpdateRequest"
                        }
                    }
                ],
                "responses": {
                    "200": {
                        "description": "OK",
                        "schema": {
                            "$ref": "#/definitions/model.Product"
                        }
                    },
                    "400": {
                        "description": "Bad Request",
                        "schema": {
                            "type": "object",
                            "additionalProperties": {
                                "type": "string"
                            }
                        }
                    },
                    "404": {
                        "description": "Not Found",
                        "schema": {
                            "type": "object",
                            "additionalProperties": {
                                "type": "string"
                            }
                        }
                    }
                }
            },
            "delete": {
                "description": "Menghapus produk berdasarkan ID",
                "produces": [
                    "application/json"
                ],
                "tags": [
                    "products"
                ],
                "summary": "Hapus produk",
                "parameters": [
                    {
                        "type": "integer",
                        "description": "Product ID",
                        "name": "id",
                        "in": "path",
                        "required": true
                    }
                ],
                "responses": {
                    "200": {
                        "description": "OK",
                        "schema": {
                            "type": "object",
                            "additionalProperties": {
                                "type": "string"
                            }
                        }
                    },
                    "404": {
                        "description": "Not Found",
                        "schema": {
                            "type": "object",
                            "additionalProperties": {
                                "type": "string"
                            }
                        }
                    }
                }
            }
        }
    },
    "definitions": {
        "model.Product": {
            "type": "object",
            "properties": {
                "id": {
                    "type": "integer",
                    "example": 1
                },
                "name": {
                    "type": "string",
                    "example": "Kopi Susu Ex"
                },
                "price": {
                    "type": "number",
                    "example": 15000
                },
                "stock": {
                    "type": "integer",
                    "example": 100
                }
            }
        },
        "model.ProductCreateRequest": {
            "type": "object",
            "properties": {
                "name": {
                    "type": "string",
                    "example": "Kopi Susu"
                },
                "price": {
                    "type": "number",
                    "example": 15000
                },
                "stock": {
                    "type": "integer",
                    "example": 100
                }
            }
        },
        "model.ProductUpdateRequest": {
            "type": "object",
            "properties": {
                "name": {
                    "type": "string",
                    "example": "Kopi Susu Gula Aren"
                },
                "price": {
                    "type": "number",
                    "example": 18000
                },
                "stock": {
                    "type": "integer",
                    "example": 80
                }
            }
        }
    }
}